sanic_json_logging/__init__.py
sanic_json_logging/formatters.py
sanic_json_logging-4.1.2.dist-info/LICENSE
sanic_json_logging-4.1.2.dist-info/WHEEL
sanic_json_logging-4.1.2.dist-info/METADATA
sanic_json_logging-4.1.2.dist-info/RECORD
