Metadata-Version: 2.1
Name: sanic-json-logging
Version: 4.1.2
Summary: Simple library to emit json formatted logs to stdout
Home-page: https://github.com/terrycain/sanic-json-logging
License: Apache-2.0
Keywords: sanic,json,logging
Author: Terry Cain
Author-email: terry@terrys-home.co.uk
Requires-Python: >=3.8,<4.0
Classifier: Development Status :: 2 - Pre-Alpha
Classifier: Intended Audience :: Developers
Classifier: License :: OSI Approved :: Apache Software License
Classifier: Natural Language :: English
Classifier: Programming Language :: Python :: 3
Classifier: Programming Language :: Python :: 3.8
Classifier: Programming Language :: Python :: 3.9
Provides-Extra: extratb
Requires-Dist: boltons (>=21.0.0); extra == "extratb"
Requires-Dist: sanic (>=21.6.0)
Project-URL: Repository, https://github.com/terrycain/sanic-json-logging
